espyta/__init__.py
espyta/__main__.py
espyta/command.py
espyta/configuration.py
espyta/http.py
espyta-0.0.0.dist-info/entry_points.txt
espyta-0.0.0.dist-info/LICENSE
espyta-0.0.0.dist-info/WHEEL
espyta-0.0.0.dist-info/METADATA
espyta-0.0.0.dist-info/RECORD
