Metadata-Version: 2.1
Name: espyta
Version: 0.0.0
Summary: Webhook handler to flash ESPs through OTA.
Home-page: https://github.com/supakeen/espyta
License: MIT
Keywords: esp,embedded
Author: supakeen
Author-email: cmdr@supakeen.com
Requires-Python: >=3.6,<4
Classifier: License :: OSI Approved :: MIT License
Classifier: Programming Language :: Python
Classifier: Programming Language :: Python :: 3
Classifier: Programming Language :: Python :: 3.6
Classifier: Programming Language :: Python :: 3.7
Classifier: Programming Language :: Python :: 3.8
Classifier: Programming Language :: Python :: 3.9
Requires-Dist: toml (>=0.10.0,<0.11.0)
Requires-Dist: tornado (>=6.0,<7.0)
Project-URL: Repository, https://github.com/supakeen/espyta
